{"634529260324782089": {"wallet": 345663615.0999999, "bank": 99979304793546, "bag": [{"item": "watch", "amount": 1}, {"item": "pc", "amount": 1}, {"item": "amy dictionary", "amount": 1}, {"item": "amy's bathwater", "amount": 1}, {"item": "big bird", "amount": 1}, {"item": "ame", "amount": 2}, {"item": "tickets to the weh museum", "amount": 1}], "property": [{"item": "mansion", "amount": 0}, {"item": "single-detached", "amount": 1}, {"item": "apartment", "amount": 0}, {"item": "townhouse", "amount": 1}, {"item": "mansion", "amount": 1}, {"item": "apartment", "amount": 1}, {"item": "mansion", "amount": 1}, {"item": "apartment", "amount": 1}]}, "306232149684781056": {"wallet": 722750233, "bank": 5000000000, "bag": [{"item": "amy's bathwater", "amount": 2}, {"item": "big bird", "amount": 2}, {"item": "amy dictionary", "amount": 1}, {"item": "ame", "amount": 5}, {"item": "tickets to the weh museum", "amount": 1}, {"item": "fruit stand", "amount": 1}], "property": [{"item": "mansion", "amount": 1}]}, "611977300816297994": {"wallet": 39903, "bank": 0, "bag": [{"item": "amy's bathwater", "amount": 1}, {"item": "big bird", "amount": 1}, {"item": "amy dictionary", "amount": 1}]}, "546499804964847642": {"wallet": 5069420, "bank": 7}, "596903710915952644": {"wallet": 1291, "bank": 0}, "832502413419741214": {"wallet": 18, "bank": 0}, "673690458492239872": {"wallet": 90111, "bank": 0, "bag": [{"item": "big bird", "amount": 69}, {"item": "amy dictionary", "amount": 1}]}, "730845817463898152": {"wallet": 336, "bank": 0, "bag": [{"item": "pc", "amount": 1}]}, "526132570438762496": {"wallet": 1248, "bank": 0}, "814231444326842469": {"wallet": 10001000, "bank": 0}, "706326876209283113": {"wallet": 442, "bank": 0}, "518122182707118101": {"wallet": -2523, "bank": 0}, "370682062623080448": {"wallet": 189, "bank": 0}, "585998468573691924": {"wallet": 905, "bank": 0, "bag": [{"item": "ame", "amount": 2}, {"item": "big bird", "amount": 1}, {"item": "amy dictionary", "amount": 1}]}, "529849286087802880": {"wallet": 0, "bank": 0}}